docx_image_extractor_mcp/__init__.py
docx_image_extractor_mcp/__main__.py
docx_image_extractor_mcp/main.py
docx_image_extractor_mcp/core/__init__.py
docx_image_extractor_mcp/core/config.py
docx_image_extractor_mcp/core/extractor.py
docx_image_extractor_mcp/interfaces/__init__.py
docx_image_extractor_mcp/interfaces/cli.py
docx_image_extractor_mcp/interfaces/mcp_server.py
docx_image_extractor_mcp-1.2.1.dist-info/licenses/LICENSE
docx_image_extractor_mcp-1.2.1.dist-info/METADATA
docx_image_extractor_mcp-1.2.1.dist-info/WHEEL
docx_image_extractor_mcp-1.2.1.dist-info/entry_points.txt
docx_image_extractor_mcp-1.2.1.dist-info/top_level.txt
docx_image_extractor_mcp-1.2.1.dist-info/RECORD
