Metadata-Version: 2.4
Name: docx-image-extractor-mcp
Version: 1.2.1
Summary: A powerful DOC/DOCX image extractor with MCP protocol support for Claude Desktop integration
Home-page: https://github.com/docx-image-extractor/docx-image-extractor-mcp
Author: DOCX Image Extractor Team
Author-email: docx.extractor@gmail.com
Project-URL: Bug Reports, https://github.com/docx-image-extractor/docx-image-extractor-mcp/issues
Project-URL: Source, https://github.com/docx-image-extractor/docx-image-extractor-mcp
Project-URL: Documentation, https://github.com/docx-image-extractor/docx-image-extractor-mcp/blob/main/README.md
Project-URL: Changelog, https://github.com/docx-image-extractor/docx-image-extractor-mcp/blob/main/CHANGELOG.md
Keywords: doc,docx,image,extractor,mcp,word,document,ole
Classifier: Development Status :: 4 - Beta
Classifier: Intended Audience :: Developers
Classifier: License :: OSI Approved :: MIT License
Classifier: Operating System :: OS Independent
Classifier: Programming Language :: Python :: 3
Classifier: Programming Language :: Python :: 3.8
Classifier: Programming Language :: Python :: 3.9
Classifier: Programming Language :: Python :: 3.10
Classifier: Programming Language :: Python :: 3.11
Classifier: Programming Language :: Python :: 3.12
Requires-Python: >=3.8
License-File: LICENSE
Requires-Dist: pypinyin>=0.47.0
Requires-Dist: mcp>=1.0.0
Requires-Dist: python-docx>=0.8.11
Requires-Dist: olefile>=0.46
Requires-Dist: docx2txt>=0.8
Dynamic: author
Dynamic: author-email
Dynamic: classifier
Dynamic: description
Dynamic: description-content-type
Dynamic: home-page
Dynamic: keywords
Dynamic: license-file
Dynamic: project-url
Dynamic: requires-dist
Dynamic: requires-python
Dynamic: summary
